nii_rs-0.1.2.dist-info/METADATA
nii_rs-0.1.2.dist-info/WHEEL
nii_rs-0.1.2.dist-info/licenses/LICENSE-APACHE
nii_rs-0.1.2.dist-info/licenses/LICENSE-MIT
nii/__init__.py
nii/_nii.cpython-312-i386-linux-gnu.so
nii_rs-0.1.2.dist-info/RECORD
