Metadata-Version: 2.4
Name: nii-rs
Version: 0.1.2
Classifier: Programming Language :: Rust
Classifier: Programming Language :: Python :: Implementation :: CPython
License-File: LICENSE-APACHE
License-File: LICENSE-MIT
Summary: Rust library for reading/writing NIfTI files, with SimpleITK/Nibabel-like APIs, native Rust support, and Python bindings for cross-language performance.
Keywords: medical-imaging,nii,nifti,nibabel,ITK
License: MIT OR Apache-2.0
Requires-Python: >=3.8
Project-URL: Source Code, https://github.com/Plasma-Blue/nii-rs
